lotr_sdk_iyerland/__init__.py
lotr_sdk_iyerland/one_api_sdk.py
lotr_sdk_iyerland-1.0.0.dist-info/LICENSE
lotr_sdk_iyerland-1.0.0.dist-info/METADATA
lotr_sdk_iyerland-1.0.0.dist-info/WHEEL
lotr_sdk_iyerland-1.0.0.dist-info/top_level.txt
lotr_sdk_iyerland-1.0.0.dist-info/RECORD
