Metadata-Version: 2.1
Name: lotr-sdk-iyerland
Version: 1.0.0
Summary: A Python SDK for The Lord Of the Rings API
Author-email: Narayan Iyer <narayan@iyers.biz>
License: MIT License
Project-URL: Homepage, https://github.com/iyerland/narayan-sdk
Project-URL: Bug Tracker, https://github.com/pypa/narayan-sdk/issues
Classifier: Programming Language :: Python :: 3
Classifier: License :: OSI Approved :: MIT License
Classifier: Operating System :: OS Independent
Requires-Python: >=3.9
License-File: LICENSE
Provides-Extra: dev
Requires-Dist: black ; extra == 'dev'
Requires-Dist: bumpver ; extra == 'dev'
Requires-Dist: isort ; extra == 'dev'
Requires-Dist: pip-tools ; extra == 'dev'
Requires-Dist: pytest ; extra == 'dev'
